[
    {
        "No": "1",
        "DateOfHighway": "",
        "StartSection": "",
        "EndSection": "",
        "Amount": 0
    },
    {
        "No": "2",
        "DateOfHighway": "",
        "StartSection": "",
        "EndSection": "",
        "Amount": 0
    },
    {
        "No": "3",
        "DateOfHighway": "",
        "StartSection": "",
        "EndSection": "",
        "Amount": 0
    },
    {
        "No": "4",
        "DateOfHighway": "",
        "StartSection": "",
        "EndSection": "",
        "Amount": 0
    },
    {
        "No": "5",
        "DateOfHighway": "",
        "StartSection": "",
        "EndSection": "",
        "Amount": 0
    },
    {
        "No": "6",
        "DateOfHighway": "",
        "StartSection": "",
        "EndSection": "",
        "Amount": 0
    },
    {
        "No": "7",
        "DateOfHighway": "",
        "StartSection": "",
        "EndSection": "",
        "Amount": 0
    },
    {
        "No": "8",
        "DateOfHighway": "",
        "StartSection": "",
        "EndSection": "",
        "Amount": 0
    },
    {
        "No": "9",
        "DateOfHighway": "",
        "StartSection": "",
        "EndSection": "",
        "Amount": 0
    },
    {
        "No": "10",
        "DateOfHighway": "",
        "StartSection": "",
        "EndSection": "",
        "Amount": 0
    },
    {
        "No": "11",
        "DateOfHighway": "",
        "StartSection": "",
        "EndSection": "",
        "Amount": 0
    },
    {
        "No": "12",
        "DateOfHighway": "",
        "StartSection": "",
        "EndSection": "",
        "Amount": 0
    }
  ]